{
    "sourceFile": "src/components/TodoCard.jsx",
    "activeCommit": 0,
    "commits": [
        {
            "activePatchIndex": 21,
            "patches": [
                {
                    "date": 1736217249417,
                    "content": "Index: \n===================================================================\n--- \n+++ \n"
                },
                {
                    "date": 1736217258833,
                    "content": "Index: \n===================================================================\n--- \n+++ \n@@ -6,9 +6,9 @@\n     <li className='todoItem'>\n         {children}\n         <div className='actionsContainer'>\n             <button onClick={() => {\n-                handleEditTodo\n+                handleEditTodo(index)\n             }}>\n             <i className=\"fa-solid fa-pen-to-square\"></i>\n             </button>\n             <button onClick={() => {\n"
                },
                {
                    "date": 1736217753313,
                    "content": "Index: \n===================================================================\n--- \n+++ \n@@ -1,22 +1,25 @@\n import React from 'react'\n \n export default function TodoCard(props) {\n-  const {children, handleDeleteTodo, index, handleEditTodo } = props\n+  const {children, handleDeleteTodo, index, handleEditTodo, handleCheckTodo, todos } = props\n+  const todo = todos[index]\n+  \n   return (\n     <li className='todoItem'>\n         {children}\n         <div className='actionsContainer'>\n-            <button onClick={() => {\n-                handleEditTodo(index)\n-            }}>\n-            <i className=\"fa-solid fa-pen-to-square\"></i>\n+            <button onClick={() => handleEditTodo(index)}>\n+                <i className=\"fa-solid fa-pen-to-square\"></i>\n             </button>\n-            <button onClick={() => {\n-                handleDeleteTodo(index)\n-            }}>\n-            <i className=\"fa-regular fa-trash-can\"></i>\n+            <button onClick={() => handleDeleteTodo(index)}>\n+                <i className=\"fa-regular fa-trash-can\"></i>\n             </button>\n+            {/* Check Button and Emoji */}\n+            <button onClick={() => handleCheckTodo(index)}>\n+                <i className={`fa-solid ${todo.isDone ? \"fa-check-circle\" : \"fa-circle\"}`}></i>\n+                {todo.isDone ? \" ✅\" : \" ⏳\"}\n+            </button>\n         </div>\n     </li>\n   )\n }\n"
                },
                {
                    "date": 1736217800878,
                    "content": "Index: \n===================================================================\n--- \n+++ \n@@ -1,25 +1,22 @@\n import React from 'react'\n \n export default function TodoCard(props) {\n-  const {children, handleDeleteTodo, index, handleEditTodo, handleCheckTodo, todos } = props\n-  const todo = todos[index]\n-  \n+  const {children, handleDeleteTodo, index, handleEditTodo } = props\n   return (\n     <li className='todoItem'>\n         {children}\n         <div className='actionsContainer'>\n-            <button onClick={() => handleEditTodo(index)}>\n-                <i className=\"fa-solid fa-pen-to-square\"></i>\n+            <button onClick={() => {\n+                handleEditTodo(index)\n+            }}>\n+            <i className=\"fa-solid fa-pen-to-square\"></i>\n             </button>\n-            <button onClick={() => handleDeleteTodo(index)}>\n-                <i className=\"fa-regular fa-trash-can\"></i>\n+            <button onClick={() => {\n+                handleDeleteTodo(index)\n+            }}>\n+            <i className=\"fa-regular fa-trash-can\"></i>\n             </button>\n-            {/* Check Button and Emoji */}\n-            <button onClick={() => handleCheckTodo(index)}>\n-                <i className={`fa-solid ${todo.isDone ? \"fa-check-circle\" : \"fa-circle\"}`}></i>\n-                {todo.isDone ? \" ✅\" : \" ⏳\"}\n-            </button>\n         </div>\n     </li>\n   )\n }\n"
                },
                {
                    "date": 1736217806856,
                    "content": "Index: \n===================================================================\n--- \n+++ \n@@ -1,22 +1,25 @@\n import React from 'react'\n \n export default function TodoCard(props) {\n-  const {children, handleDeleteTodo, index, handleEditTodo } = props\n+  const {children, handleDeleteTodo, index, handleEditTodo, handleCheckTodo, todos } = props\n+  const todo = todos[index]\n+  \n   return (\n     <li className='todoItem'>\n         {children}\n         <div className='actionsContainer'>\n-            <button onClick={() => {\n-                handleEditTodo(index)\n-            }}>\n-            <i className=\"fa-solid fa-pen-to-square\"></i>\n+            <button onClick={() => handleEditTodo(index)}>\n+                <i className=\"fa-solid fa-pen-to-square\"></i>\n             </button>\n-            <button onClick={() => {\n-                handleDeleteTodo(index)\n-            }}>\n-            <i className=\"fa-regular fa-trash-can\"></i>\n+            <button onClick={() => handleDeleteTodo(index)}>\n+                <i className=\"fa-regular fa-trash-can\"></i>\n             </button>\n+            {/* Check Button and Emoji */}\n+            <button onClick={() => handleCheckTodo(index)}>\n+                <i className={`fa-solid ${todo.isDone ? \"fa-check-circle\" : \"fa-circle\"}`}></i>\n+                {todo.isDone ? \" ✅\" : \" ⏳\"}\n+            </button>\n         </div>\n     </li>\n   )\n }\n"
                },
                {
                    "date": 1736218087016,
                    "content": "Index: \n===================================================================\n--- \n+++ \n@@ -1,24 +1,23 @@\n import React from 'react'\n \n export default function TodoCard(props) {\n-  const {children, handleDeleteTodo, index, handleEditTodo, handleCheckTodo, todos } = props\n+  const { children, handleDeleteTodo, index, handleEditTodo, handleCheckTodo, todos } = props\n   const todo = todos[index]\n-  \n+\n   return (\n-    <li className='todoItem'>\n+    <li className={`todoItem ${todo.isDone ? 'done' : ''}`}>\n         {children}\n         <div className='actionsContainer'>\n             <button onClick={() => handleEditTodo(index)}>\n                 <i className=\"fa-solid fa-pen-to-square\"></i>\n             </button>\n             <button onClick={() => handleDeleteTodo(index)}>\n                 <i className=\"fa-regular fa-trash-can\"></i>\n             </button>\n-            {/* Check Button and Emoji */}\n+            {/* Check Button */}\n             <button onClick={() => handleCheckTodo(index)}>\n-                <i className={`fa-solid ${todo.isDone ? \"fa-check-circle\" : \"fa-circle\"}`}></i>\n-                {todo.isDone ? \" ✅\" : \" ⏳\"}\n+                <i className={`fa-solid fa-check ${todo.isDone ? 'checked' : ''}`}></i>\n             </button>\n         </div>\n     </li>\n   )\n"
                },
                {
                    "date": 1736218092943,
                    "content": "Index: \n===================================================================\n--- \n+++ \n@@ -13,9 +13,9 @@\n             </button>\n             <button onClick={() => handleDeleteTodo(index)}>\n                 <i className=\"fa-regular fa-trash-can\"></i>\n             </button>\n-            {/* Check Button */}\n+\n             <button onClick={() => handleCheckTodo(index)}>\n                 <i className={`fa-solid fa-check ${todo.isDone ? 'checked' : ''}`}></i>\n             </button>\n         </div>\n"
                },
                {
                    "date": 1736218202191,
                    "content": "Index: \n===================================================================\n--- \n+++ \n@@ -1,24 +1,22 @@\n import React from 'react'\n \n export default function TodoCard(props) {\n-  const { children, handleDeleteTodo, index, handleEditTodo, handleCheckTodo, todos } = props\n-  const todo = todos[index]\n-\n+  const {children, handleDeleteTodo, index, handleEditTodo } = props\n   return (\n-    <li className={`todoItem ${todo.isDone ? 'done' : ''}`}>\n+    <li className='todoItem'>\n         {children}\n         <div className='actionsContainer'>\n-            <button onClick={() => handleEditTodo(index)}>\n-                <i className=\"fa-solid fa-pen-to-square\"></i>\n+            <button onClick={() => {\n+                handleEditTodo(index)\n+            }}>\n+            <i className=\"fa-solid fa-pen-to-square\"></i>\n             </button>\n-            <button onClick={() => handleDeleteTodo(index)}>\n-                <i className=\"fa-regular fa-trash-can\"></i>\n+            <button onClick={() => {\n+                handleDeleteTodo(index)\n+            }}>\n+            <i className=\"fa-regular fa-trash-can\"></i>\n             </button>\n-\n-            <button onClick={() => handleCheckTodo(index)}>\n-                <i className={`fa-solid fa-check ${todo.isDone ? 'checked' : ''}`}></i>\n-            </button>\n         </div>\n     </li>\n   )\n }\n"
                },
                {
                    "date": 1736218207402,
                    "content": "Index: \n===================================================================\n--- \n+++ \n@@ -6,9 +6,9 @@\n     <li className='todoItem'>\n         {children}\n         <div className='actionsContainer'>\n             <button onClick={() => {\n-                handleEditTodo(index)\n+                handleEditTodo()\n             }}>\n             <i className=\"fa-solid fa-pen-to-square\"></i>\n             </button>\n             <button onClick={() => {\n"
                },
                {
                    "date": 1736218238011,
                    "content": "Index: \n===================================================================\n--- \n+++ \n@@ -1,22 +1,25 @@\n import React from 'react'\n \n export default function TodoCard(props) {\n-  const {children, handleDeleteTodo, index, handleEditTodo } = props\n+  const { children, handleDeleteTodo, index, handleEditTodo, handleCheckTodo, todos } = props\n+  const todo = todos[index]\n+\n   return (\n-    <li className='todoItem'>\n+    <li className={`todoItem ${todo.isDone ? 'done' : ''}`}>\n         {children}\n         <div className='actionsContainer'>\n-            <button onClick={() => {\n-                handleEditTodo()\n-            }}>\n-            <i className=\"fa-solid fa-pen-to-square\"></i>\n+            <button onClick={() => handleEditTodo(index)}>\n+                <i className=\"fa-solid fa-pen-to-square\"></i>\n             </button>\n-            <button onClick={() => {\n-                handleDeleteTodo(index)\n-            }}>\n-            <i className=\"fa-regular fa-trash-can\"></i>\n+            \n+            <button onClick={() => handleDeleteTodo(index)}>\n+                <i className=\"fa-regular fa-trash-can\"></i>\n             </button>\n+\n+            <button onClick={() => handleCheckTodo(index)}>\n+                <i className={`fa-solid fa-check ${todo.isDone ? 'checked' : ''}`}></i>\n+            </button>\n         </div>\n     </li>\n   )\n }\n"
                },
                {
                    "date": 1736218358974,
                    "content": "Index: \n===================================================================\n--- \n+++ \n@@ -0,0 +1,25 @@\n+import React from 'react'\n+\n+export default function TodoCard(props) {\n+  const { children, handleDeleteTodo, index, handleEditTodo, handleCheckTodo, todos } = props\n+  const todo = todos[index]\n+\n+  return (\n+    <li className={`todoItem ${todo.isDone ? 'done' : ''}`}>\n+        {children}\n+        <div className='actionsContainer'>\n+            <button onClick={() => handleEditTodo(index)}>\n+                <i className=\"fa-solid fa-pen-to-square\"></i>\n+            </button>\n+            \n+            <button onClick={() => handleDeleteTodo(index)}>\n+                <i className=\"fa-regular fa-trash-can\"></i>\n+            </button>\n+\n+            <button onClick={() => handleCheckTodo(index)}>\n+                <i className={`fa-solid fa-check ${todo.isDone ? 'checked' : ''}`}></i>\n+            </button>\n+        </div>\n+    </li>\n+  )\n+}\n"
                },
                {
                    "date": 1736218367621,
                    "content": "Index: \n===================================================================\n--- \n+++ \n@@ -22,29 +22,4 @@\n         </div>\n     </li>\n   )\n }\n-import React from 'react'\n-\n-export default function TodoCard(props) {\n-  const { children, handleDeleteTodo, index, handleEditTodo, handleCheckTodo, todos } = props\n-  const todo = todos[index]\n-\n-  return (\n-    <li className={`todoItem ${todo.isDone ? 'done' : ''}`}>\n-        {children}\n-        <div className='actionsContainer'>\n-            <button onClick={() => handleEditTodo(index)}>\n-                <i className=\"fa-solid fa-pen-to-square\"></i>\n-            </button>\n-            \n-            <button onClick={() => handleDeleteTodo(index)}>\n-                <i className=\"fa-regular fa-trash-can\"></i>\n-            </button>\n-\n-            <button onClick={() => handleCheckTodo(index)}>\n-                <i className={`fa-solid fa-check ${todo.isDone ? 'checked' : ''}`}></i>\n-            </button>\n-        </div>\n-    </li>\n-  )\n-}\n"
                },
                {
                    "date": 1736218582572,
                    "content": "Index: \n===================================================================\n--- \n+++ \n@@ -7,16 +7,27 @@\n   return (\n     <li className={`todoItem ${todo.isDone ? 'done' : ''}`}>\n         {children}\n         <div className='actionsContainer'>\n-            <button onClick={() => handleEditTodo(index)}>\n+            {/* Edit Button */}\n+            <button onClick={() => {\n+                if (window.confirm(\"Are you sure you want to edit this item?\")) {\n+                    handleEditTodo(index);\n+                }\n+            }}>\n                 <i className=\"fa-solid fa-pen-to-square\"></i>\n             </button>\n             \n-            <button onClick={() => handleDeleteTodo(index)}>\n+            {/* Delete Button */}\n+            <button onClick={() => {\n+                if (window.confirm(\"Are you sure you want to delete this item?\")) {\n+                    handleDeleteTodo(index);\n+                }\n+            }}>\n                 <i className=\"fa-regular fa-trash-can\"></i>\n             </button>\n \n+            {/* Check Button */}\n             <button onClick={() => handleCheckTodo(index)}>\n                 <i className={`fa-solid fa-check ${todo.isDone ? 'checked' : ''}`}></i>\n             </button>\n         </div>\n"
                },
                {
                    "date": 1736218741735,
                    "content": "Index: \n===================================================================\n--- \n+++ \n@@ -8,22 +8,14 @@\n     <li className={`todoItem ${todo.isDone ? 'done' : ''}`}>\n         {children}\n         <div className='actionsContainer'>\n             {/* Edit Button */}\n-            <button onClick={() => {\n-                if (window.confirm(\"Are you sure you want to edit this item?\")) {\n-                    handleEditTodo(index);\n-                }\n-            }}>\n+            <button onClick={() => handleEditTodo(index)}>\n                 <i className=\"fa-solid fa-pen-to-square\"></i>\n             </button>\n             \n             {/* Delete Button */}\n-            <button onClick={() => {\n-                if (window.confirm(\"Are you sure you want to delete this item?\")) {\n-                    handleDeleteTodo(index);\n-                }\n-            }}>\n+            <button onClick={() => handleDeleteTodo(index)}>\n                 <i className=\"fa-regular fa-trash-can\"></i>\n             </button>\n \n             {/* Check Button */}\n"
                },
                {
                    "date": 1736218880685,
                    "content": "Index: \n===================================================================\n--- \n+++ \n@@ -0,0 +1,36 @@\n+import React from 'react'\n+\n+export default function TodoCard(props) {\n+  const { children, handleDeleteTodo, index, handleEditTodo, handleCheckTodo, todos } = props\n+  const todo = todos[index]\n+\n+  return (\n+    <li className={`todoItem ${todo.isDone ? 'done' : ''}`}>\n+        {children}\n+        <div className='actionsContainer'>\n+            {/* Edit Button */}\n+            <button onClick={() => {\n+                if (window.confirm(\"Are you sure you want to edit this item?\")) {\n+                    handleEditTodo(index);\n+                }\n+            }}>\n+                <i className=\"fa-solid fa-pen-to-square\"></i>\n+            </button>\n+            \n+            {/* Delete Button */}\n+            <button onClick={() => {\n+                if (window.confirm(\"Are you sure you want to delete this item?\")) {\n+                    handleDeleteTodo(index);\n+                }\n+            }}>\n+                <i className=\"fa-regular fa-trash-can\"></i>\n+            </button>\n+\n+            {/* Check Button */}\n+            <button onClick={() => handleCheckTodo(index)}>\n+                <i className={`fa-solid fa-check ${todo.isDone ? 'checked' : ''}`}></i>\n+            </button>\n+        </div>\n+    </li>\n+  )\n+}\n"
                },
                {
                    "date": 1736218889066,
                    "content": "Index: \n===================================================================\n--- \n+++ \n@@ -7,55 +7,16 @@\n   return (\n     <li className={`todoItem ${todo.isDone ? 'done' : ''}`}>\n         {children}\n         <div className='actionsContainer'>\n-            {/* Edit Button */}\n-            <button onClick={() => {\n-                if (window.confirm(\"Are you sure you want to edit this item?\")) {\n-                    handleEditTodo(index);\n-                }\n-            }}>\n-                <i className=\"fa-solid fa-pen-to-square\"></i>\n-            </button>\n-            \n-            {/* Delete Button */}\n-            <button onClick={() => {\n-                if (window.confirm(\"Are you sure you want to delete this item?\")) {\n-                    handleDeleteTodo(index);\n-                }\n-            }}>\n-                <i className=\"fa-regular fa-trash-can\"></i>\n-            </button>\n-\n-            {/* Check Button */}\n-            <button onClick={() => handleCheckTodo(index)}>\n-                <i className={`fa-solid fa-check ${todo.isDone ? 'checked' : ''}`}></i>\n-            </button>\n-        </div>\n-    </li>\n-  )\n-}\n-import React from 'react'\n-\n-export default function TodoCard(props) {\n-  const { children, handleDeleteTodo, index, handleEditTodo, handleCheckTodo, todos } = props\n-  const todo = todos[index]\n-\n-  return (\n-    <li className={`todoItem ${todo.isDone ? 'done' : ''}`}>\n-        {children}\n-        <div className='actionsContainer'>\n-            {/* Edit Button */}\n             <button onClick={() => handleEditTodo(index)}>\n                 <i className=\"fa-solid fa-pen-to-square\"></i>\n             </button>\n             \n-            {/* Delete Button */}\n             <button onClick={() => handleDeleteTodo(index)}>\n                 <i className=\"fa-regular fa-trash-can\"></i>\n             </button>\n \n-            {/* Check Button */}\n             <button onClick={() => handleCheckTodo(index)}>\n                 <i className={`fa-solid fa-check ${todo.isDone ? 'checked' : ''}`}></i>\n             </button>\n         </div>\n"
                },
                {
                    "date": 1736218944185,
                    "content": "Index: \n===================================================================\n--- \n+++ \n@@ -7,16 +7,19 @@\n   return (\n     <li className={`todoItem ${todo.isDone ? 'done' : ''}`}>\n         {children}\n         <div className='actionsContainer'>\n+            {/* Edit Button */}\n             <button onClick={() => handleEditTodo(index)}>\n                 <i className=\"fa-solid fa-pen-to-square\"></i>\n             </button>\n             \n+            {/* Delete Button */}\n             <button onClick={() => handleDeleteTodo(index)}>\n                 <i className=\"fa-regular fa-trash-can\"></i>\n             </button>\n \n+            {/* Check Button */}\n             <button onClick={() => handleCheckTodo(index)}>\n                 <i className={`fa-solid fa-check ${todo.isDone ? 'checked' : ''}`}></i>\n             </button>\n         </div>\n"
                },
                {
                    "date": 1736218952046,
                    "content": "Index: \n===================================================================\n--- \n+++ \n@@ -8,14 +8,22 @@\n     <li className={`todoItem ${todo.isDone ? 'done' : ''}`}>\n         {children}\n         <div className='actionsContainer'>\n             {/* Edit Button */}\n-            <button onClick={() => handleEditTodo(index)}>\n+            <button onClick={() => {\n+                if (window.confirm(\"Are you sure you want to edit this item?\")) {\n+                    handleEditTodo(index);\n+                }\n+            }}>\n                 <i className=\"fa-solid fa-pen-to-square\"></i>\n             </button>\n             \n             {/* Delete Button */}\n-            <button onClick={() => handleDeleteTodo(index)}>\n+            <button onClick={() => {\n+                if (window.confirm(\"Are you sure you want to delete this item?\")) {\n+                    handleDeleteTodo(index);\n+                }\n+            }}>\n                 <i className=\"fa-regular fa-trash-can\"></i>\n             </button>\n \n             {/* Check Button */}\n"
                },
                {
                    "date": 1736219578714,
                    "content": "Index: \n===================================================================\n--- \n+++ \n@@ -8,13 +8,9 @@\n     <li className={`todoItem ${todo.isDone ? 'done' : ''}`}>\n         {children}\n         <div className='actionsContainer'>\n             {/* Edit Button */}\n-            <button onClick={() => {\n-                if (window.confirm(\"Are you sure you want to edit this item?\")) {\n-                    handleEditTodo(index);\n-                }\n-            }}>\n+            <button onClick={() => handleEditTodo(index)}>\n                 <i className=\"fa-solid fa-pen-to-square\"></i>\n             </button>\n             \n             {/* Delete Button */}\n"
                },
                {
                    "date": 1736219879070,
                    "content": "Index: \n===================================================================\n--- \n+++ \n@@ -8,9 +8,13 @@\n     <li className={`todoItem ${todo.isDone ? 'done' : ''}`}>\n         {children}\n         <div className='actionsContainer'>\n             {/* Edit Button */}\n-            <button onClick={() => handleEditTodo(index)}>\n+            <button onClick={() => {\n+                if (window.confirm(\"Are you sure you want to edit this item?\")) {\n+                    handleEditTodo(index);\n+                }\n+            }}>\n                 <i className=\"fa-solid fa-pen-to-square\"></i>\n             </button>\n             \n             {/* Delete Button */}\n@@ -22,9 +26,12 @@\n                 <i className=\"fa-regular fa-trash-can\"></i>\n             </button>\n \n             {/* Check Button */}\n-            <button onClick={() => handleCheckTodo(index)}>\n+            <button \n+              onClick={() => handleCheckTodo(index)} \n+              disabled={todo.isDone}  {/* Disable Check Button if task is completed */}\n+            >\n                 <i className={`fa-solid fa-check ${todo.isDone ? 'checked' : ''}`}></i>\n             </button>\n         </div>\n     </li>\n"
                },
                {
                    "date": 1736219959151,
                    "content": "Index: \n===================================================================\n--- \n+++ \n@@ -8,13 +8,9 @@\n     <li className={`todoItem ${todo.isDone ? 'done' : ''}`}>\n         {children}\n         <div className='actionsContainer'>\n             {/* Edit Button */}\n-            <button onClick={() => {\n-                if (window.confirm(\"Are you sure you want to edit this item?\")) {\n-                    handleEditTodo(index);\n-                }\n-            }}>\n+            <button onClick={() => handleEditTodo(index)}>\n                 <i className=\"fa-solid fa-pen-to-square\"></i>\n             </button>\n             \n             {/* Delete Button */}\n"
                },
                {
                    "date": 1736219978563,
                    "content": "Index: \n===================================================================\n--- \n+++ \n@@ -7,26 +7,23 @@\n   return (\n     <li className={`todoItem ${todo.isDone ? 'done' : ''}`}>\n         {children}\n         <div className='actionsContainer'>\n-            {/* Edit Button */}\n             <button onClick={() => handleEditTodo(index)}>\n                 <i className=\"fa-solid fa-pen-to-square\"></i>\n             </button>\n             \n-            {/* Delete Button */}\n             <button onClick={() => {\n                 if (window.confirm(\"Are you sure you want to delete this item?\")) {\n                     handleDeleteTodo(index);\n                 }\n             }}>\n                 <i className=\"fa-regular fa-trash-can\"></i>\n             </button>\n \n-            {/* Check Button */}\n             <button \n               onClick={() => handleCheckTodo(index)} \n-              disabled={todo.isDone}  {/* Disable Check Button if task is completed */}\n+              disabled={todo.isDone}\n             >\n                 <i className={`fa-solid fa-check ${todo.isDone ? 'checked' : ''}`}></i>\n             </button>\n         </div>\n"
                }
            ],
            "date": 1736217249417,
            "name": "Commit-0",
            "content": "import React from 'react'\n\nexport default function TodoCard(props) {\n  const {children, handleDeleteTodo, index, handleEditTodo } = props\n  return (\n    <li className='todoItem'>\n        {children}\n        <div className='actionsContainer'>\n            <button onClick={() => {\n                handleEditTodo\n            }}>\n            <i className=\"fa-solid fa-pen-to-square\"></i>\n            </button>\n            <button onClick={() => {\n                handleDeleteTodo(index)\n            }}>\n            <i className=\"fa-regular fa-trash-can\"></i>\n            </button>\n        </div>\n    </li>\n  )\n}\n"
        }
    ]
}